h2o_notebook_theme/__init__.py
h2o_notebook_theme/_version.py
h2o_notebook_theme-0.4.2.data/data/share/jupyter/labextensions/h2o-notebook-theme/package.json
h2o_notebook_theme-0.4.2.data/data/share/jupyter/labextensions/h2o-notebook-theme/static/509.ec3d7ee8f99089574276.js
h2o_notebook_theme-0.4.2.data/data/share/jupyter/labextensions/h2o-notebook-theme/static/remoteEntry.e260293ed5e652a7019b.js
h2o_notebook_theme-0.4.2.data/data/share/jupyter/labextensions/h2o-notebook-theme/static/style.js
h2o_notebook_theme-0.4.2.data/data/share/jupyter/labextensions/h2o-notebook-theme/static/third-party-licenses.json
h2o_notebook_theme-0.4.2.data/data/share/jupyter/labextensions/h2o-notebook-theme/themes/h2o-notebook-theme/39e72c0794c12f2dbb14.woff2
h2o_notebook_theme-0.4.2.data/data/share/jupyter/labextensions/h2o-notebook-theme/themes/h2o-notebook-theme/eaeb14a925874adf1492.woff2
h2o_notebook_theme-0.4.2.data/data/share/jupyter/labextensions/h2o-notebook-theme/themes/h2o-notebook-theme/index.css
h2o_notebook_theme-0.4.2.data/data/share/jupyter/labextensions/h2o-notebook-theme/themes/h2o-notebook-theme/index.js
h2o_notebook_theme-0.4.2.data/data/share/jupyter/labextensions/h2o-notebook-theme/themes/h2o-notebook-theme/logo.svg
h2o_notebook_theme-0.4.2.data/data/share/jupyter/labextensions/h2o-notebook-theme/install.json
h2o_notebook_theme-0.4.2.dist-info/METADATA
h2o_notebook_theme-0.4.2.dist-info/WHEEL
h2o_notebook_theme-0.4.2.dist-info/licenses/LICENSE
h2o_notebook_theme-0.4.2.dist-info/RECORD
