Metadata-Version: 2.3
Name: h2o_notebook_theme
Version: 0.4.2
Dynamic: Keywords
Summary: H2O.ai JupyterLab Theme
Project-URL: Homepage, https://github.com/h2oai/notebook-theme
Project-URL: Bug Tracker, https://github.com/h2oai/notebook-theme/issues
Project-URL: Repository, https://github.com/h2oai/notebook-theme.git
Author-email: "H2O.ai" <support@h2o.ai>
License: BSD 3-Clause License
License-File: LICENSE
Classifier: Framework :: Jupyter
Classifier: Framework :: Jupyter :: JupyterLab
Classifier: Framework :: Jupyter :: JupyterLab :: 4
Classifier: Framework :: Jupyter :: JupyterLab :: Extensions
Classifier: Framework :: Jupyter :: JupyterLab :: Extensions :: Prebuilt
Classifier: License :: OSI Approved :: BSD License
Classifier: Programming Language :: Python
Classifier: Programming Language :: Python :: 3
Classifier: Programming Language :: Python :: 3.8
Classifier: Programming Language :: Python :: 3.9
Classifier: Programming Language :: Python :: 3.10
Classifier: Programming Language :: Python :: 3.11
Classifier: Programming Language :: Python :: 3.12
Requires-Python: >=3.8
